benchmark_builder/__init__.py
benchmark_builder/class_names.py
benchmark_builder/main.py
benchmark_builder/templates.py
benchmark_builder/utils.py
benchmark_builder/benchmarks/__init__.py
benchmark_builder/benchmarks/sundataset.py
unibench/__init__.py
unibench/evaluator.py
unibench/output.py
unibench/benchmarks_zoo/__init__.py
unibench/benchmarks_zoo/benchmarks.py
unibench/benchmarks_zoo/registry.py
unibench/benchmarks_zoo/wrappers/__init__.py
unibench/benchmarks_zoo/wrappers/bechmark_handler.py
unibench/benchmarks_zoo/wrappers/huggingface.py
unibench/common_utils/__init__.py
unibench/common_utils/constants.py
unibench/common_utils/utils.py
unibench/models_zoo/__init__.py
unibench/models_zoo/models.py
unibench/models_zoo/registry.py
unibench/models_zoo/wrappers/__init__.py
unibench/models_zoo/wrappers/base.py
unibench/models_zoo/wrappers/blip.py
unibench/models_zoo/wrappers/clip.py
unibench/models_zoo/wrappers/huggingface.py
unibench/models_zoo/wrappers/lit.py
unibench/models_zoo/wrappers/transformations/__init__.py
unibench/models_zoo/wrappers/transformations/faceblur.py
unibench/models_zoo/wrappers/transformations/grayscale2rgb.py
unibench/models_zoo/wrappers/xvlm_util/__init__.py
unibench/models_zoo/wrappers/xvlm_util/box_ops.py
unibench/models_zoo/wrappers/xvlm_util/clip_vit.py
unibench/models_zoo/wrappers/xvlm_util/swin_transformer.py
unibench/models_zoo/wrappers/xvlm_util/tokenization_bert.py
unibench/models_zoo/wrappers/xvlm_util/tokenization_roberta.py
unibench/models_zoo/wrappers/xvlm_util/utils.py
unibench/models_zoo/wrappers/xvlm_util/vit.py
unibench/models_zoo/wrappers/xvlm_util/xbert.py
unibench/models_zoo/wrappers/xvlm_util/xroberta.py
unibench/models_zoo/wrappers/xvlm_util/xvlm.py
unibench-0.4.0.dist-info/licenses/LICENSE
unibench-0.4.0.dist-info/METADATA
unibench-0.4.0.dist-info/WHEEL
unibench-0.4.0.dist-info/dependency_links.txt
unibench-0.4.0.dist-info/entry_points.txt
unibench-0.4.0.dist-info/top_level.txt
unibench-0.4.0.dist-info/RECORD
