Metadata-Version: 2.4
Name: unibench
Version: 0.4.0
Summary: This repository is designed to simplify the evaluation process of vision-language models. It provides a comprehensive set of tools and scripts for evaluating VLM models and benchmarks.
Home-page: https://github.com/facebookresearch/unibench
Author: Haider Al-Tahan
Author-email: haideraltahan@meta.com
Project-URL: Bug Tracker, https://github.com/facebookresearch/unibench/issues
Classifier: Programming Language :: Python :: 3
Classifier: License :: OSI Approved :: MIT License
Classifier: Operating System :: OS Independent
Requires-Python: >=3.8
License-File: LICENSE
Requires-Dist: open-clip-torch
Requires-Dist: openai-clip
Requires-Dist: zipp
Requires-Dist: timm
Requires-Dist: fire
Requires-Dist: opencv-python
Requires-Dist: datasets
Requires-Dist: ftfy
Requires-Dist: torch
Requires-Dist: scipy
Requires-Dist: fairscale
Requires-Dist: GitPython
Requires-Dist: torchvision
Requires-Dist: rich
Requires-Dist: oslo.concurrency
Requires-Dist: transformers
Requires-Dist: gdown
Dynamic: author
Dynamic: author-email
Dynamic: classifier
Dynamic: description
Dynamic: description-content-type
Dynamic: home-page
Dynamic: license-file
Dynamic: project-url
Dynamic: requires-dist
Dynamic: requires-python
Dynamic: summary
